<?xml version="1.0"?>
<comp:component-backend-db xmlns:comp="http://openoffice.org/extensionmanager/component-registry/2010"><comp:component url="vnd.sun.star.expand:$UNO_USER_PACKAGES_CACHE/uno_packages/lu3850156yqn.tmp_/codehighlighter2.oxt/python/highlight.py"><comp:java-type-library>false</comp:java-type-library><comp:implementation-names><comp:name>ooo.ext.code-highlighter.impl</comp:name></comp:implementation-names></comp:component><comp:component url="vnd.sun.star.expand:$UNO_USER_PACKAGES_CACHE/uno_packages/lu3439852hco.tmp_/LanguageTool-20240306-snapshot.oxt/languagetool-office-extension-6.4-SNAPSHOT.jar"><comp:java-type-library>true</comp:java-type-library><comp:implementation-names><comp:name>org.languagetool.openoffice.LtSpellChecker</comp:name><comp:name>org.languagetool.openoffice.Main</comp:name></comp:implementation-names></comp:component></comp:component-backend-db>
